[
  {
    "phone": "5491123456789",
    "name": "María García",
    "company": "Empresa Ejemplo S.A.",
    "systems": ["Sistema de Facturación"],
    "knowledgeDocs": ["medilab-knowledge.md"],
    "notes": "Usuaria principal del módulo de facturación"
  },
  {
    "phone": "5492657201291",
    "name": "Ignacio Becher",
    "company": "Medilab",
    "systems": ["Plataforma de Gestión de de ART"],
    "knowledgeDocs": ["cima-knowledge.md"],
    "notes": "Reporta problemas frecuentes con la pasarela de pagos"
  }
]
